{
  "template_group": "HC",
  "profiles": [
    {
      "roi_id": "ROI_001",
      "roi_name": "Superior Parietal",
      "depth_percent": [
        0,
        10,
        20,
        30,
        40,
        50,
        60,
        70,
        80,
        90,
        100
      ],
      "ri_values": [
        0.515,
        0.6196,
        0.7024,
        0.7604,
        0.7941,
        0.805,
        0.7941,
        0.7604,
        0.7024,
        0.6196,
        0.515
      ]
    },
    {
      "roi_id": "ROI_002",
      "roi_name": "Precuneus",
      "depth_percent": [
        0,
        10,
        20,
        30,
        40,
        50,
        60,
        70,
        80,
        90,
        100
      ],
      "ri_values": [
        0.515,
        0.6196,
        0.7024,
        0.7604,
        0.7941,
        0.805,
        0.7941,
        0.7604,
        0.7024,
        0.6196,
        0.515
      ]
    },
    {
      "roi_id": "ROI_003",
      "roi_name": "Posterior Cingulate",
      "depth_percent": [
        0,
        10,
        20,
        30,
        40,
        50,
        60,
        70,
        80,
        90,
        100
      ],
      "ri_values": [
        0.515,
        0.6196,
        0.7024,
        0.7604,
        0.7941,
        0.805,
        0.7941,
        0.7604,
        0.7024,
        0.6196,
        0.515
      ]
    },
    {
      "roi_id": "ROI_004",
      "roi_name": "Inferior Parietal",
      "depth_percent": [
        0,
        10,
        20,
        30,
        40,
        50,
        60,
        70,
        80,
        90,
        100
      ],
      "ri_values": [
        0.515,
        0.6196,
        0.7024,
        0.7604,
        0.7941,
        0.805,
        0.7941,
        0.7604,
        0.7024,
        0.6196,
        0.515
      ]
    },
    {
      "roi_id": "ROI_005",
      "roi_name": "Middle Temporal",
      "depth_percent": [
        0,
        10,
        20,
        30,
        40,
        50,
        60,
        70,
        80,
        90,
        100
      ],
      "ri_values": [
        0.515,
        0.6196,
        0.7024,
        0.7604,
        0.7941,
        0.805,
        0.7941,
        0.7604,
        0.7024,
        0.6196,
        0.515
      ]
    },
    {
      "roi_id": "ROI_006",
      "roi_name": "Medial Frontal",
      "depth_percent": [
        0,
        10,
        20,
        30,
        40,
        50,
        60,
        70,
        80,
        90,
        100
      ],
      "ri_values": [
        0.515,
        0.6196,
        0.7024,
        0.7604,
        0.7941,
        0.805,
        0.7941,
        0.7604,
        0.7024,
        0.6196,
        0.515
      ]
    }
  ]
}
